CHIP_IO/GPIO.so
CHIP_IO/OverlayManager.py
CHIP_IO/SERVO.so
CHIP_IO/__init__.py
CHIP_IO/PWM.so
CHIP_IO/SOFTPWM.so
CHIP_IO/LRADC.py
CHIP_IO/Utilities.py
CHIP_IO-0.7.1.dist-info/metadata.json
CHIP_IO-0.7.1.dist-info/LICENSE.txt
CHIP_IO-0.7.1.dist-info/top_level.txt
CHIP_IO-0.7.1.dist-info/WHEEL
CHIP_IO-0.7.1.dist-info/METADATA
CHIP_IO-0.7.1.dist-info/DESCRIPTION.rst
CHIP_IO-0.7.1.dist-info/RECORD
