Metadata-Version: 1.1
Name: CHIP_IO
Version: 0.7.1
Summary: A module to control CHIP IO channels
Home-page: https://github.com/xtacocorex/CHIP_IO/
Author: Robert Wolterman
Author-email: robert.wolterman@gmail.com
License: MIT
Keywords: CHIP NextThingCo IO GPIO PWM ADC GR8 R8
Platform: UNKNOWN
Classifier: Development Status :: 3 - Alpha
Classifier: Operating System :: POSIX :: Linux
Classifier: License :: OSI Approved :: MIT License
Classifier: Intended Audience :: Developers
Classifier: Programming Language :: Python :: 2.7
Classifier: Programming Language :: Python :: 3
Classifier: Topic :: Software Development
Classifier: Topic :: Home Automation
Classifier: Topic :: System :: Hardware
